mylaps_client_wrapper.py
examples/__init__.py
examples/export_announcements.py
examples/export_championships.py
examples/export_events.py
examples/export_full_dump.py
examples/export_lap_chart.py
examples/export_laps.py
examples/export_results.py
examples/export_sessions.py
examples/export_track_records.py
examples/get_fastest_records.py
examples/__pycache__/__init__.cpython-311.pyc
examples/processing/README_PROCESSING.md
examples/processing/__init__.py
examples/processing/extract_announcements_to_csv.py
examples/processing/extract_events_to_csv.py
examples/processing/extract_laps_to_csv.py
examples/processing/extract_sessions_to_csv.py
examples/processing/ndjson_to_sqlite.py
examples/processing/processor_cli.py
examples/processing/__pycache__/__init__.cpython-311.pyc
examples/processing/__pycache__/extract_announcements_to_csv.cpython-311.pyc
examples/processing/__pycache__/extract_laps_to_csv.cpython-311.pyc
examples/processing/__pycache__/extract_sessions_to_csv.cpython-311.pyc
examples/processing/__pycache__/ndjson_to_sqlite.cpython-311.pyc
speedhive_tools-0.1.7.dist-info/licenses/LICENSE
speedhive_tools-0.1.7.dist-info/METADATA
speedhive_tools-0.1.7.dist-info/WHEEL
speedhive_tools-0.1.7.dist-info/entry_points.txt
speedhive_tools-0.1.7.dist-info/top_level.txt
speedhive_tools-0.1.7.dist-info/RECORD
