Metadata-Version: 2.4
Name: speedhive-tools
Version: 0.1.7
Summary: Utilities for the MyLaps Event Results API
Home-page: https://github.com/ncrosty58/speedhive-tools
Author: Nathan Crosty
Author-email: ncrosty58@example.com
License: MIT
Classifier: Development Status :: 3 - Alpha
Classifier: Intended Audience :: Developers
Classifier: License :: OSI Approved :: MIT License
Classifier: Programming Language :: Python :: 3 :: Only
Classifier: Programming Language :: Python :: 3.10
Requires-Python: >=3.10
License-File: LICENSE
Requires-Dist: httpx<0.29.0,>=0.23.0
Requires-Dist: attrs>=22.2.0
Requires-Dist: python-dateutil>=2.8.0
Dynamic: license-file
